webrequests/__init__.py
webrequests/core.py
webrequests/util.py
webrequests/version.json
webrequests-1.0.8.dist-info/METADATA
webrequests-1.0.8.dist-info/WHEEL
webrequests-1.0.8.dist-info/top_level.txt
webrequests-1.0.8.dist-info/RECORD
