Metadata-Version: 2.1
Name: webrequests
Version: 1.0.8
Summary: A simple wrapper of requests, simple but useful!
Home-page: https://github.com/suqingdong/webrequests
Author: suqingdong
Author-email: suqingdong1114@gmail.com
License: BSD License
Platform: UNKNOWN
Classifier: Development Status :: 5 - Production/Stable
Classifier: Operating System :: OS Independent
Classifier: Intended Audience :: Developers
Classifier: License :: OSI Approved :: BSD License
Classifier: Programming Language :: Python
Classifier: Programming Language :: Python :: 3
Classifier: Programming Language :: Python :: 3.6
Classifier: Topic :: Software Development :: Libraries
